nodestream/__init__.py
nodestream/cli/__init__.py
nodestream/cli/application.py
nodestream/cli/commands/__init__.py
nodestream/cli/commands/audit_command.py
nodestream/cli/commands/copy.py
nodestream/cli/commands/make_migrations.py
nodestream/cli/commands/new.py
nodestream/cli/commands/nodestream_command.py
nodestream/cli/commands/print_schema.py
nodestream/cli/commands/remove.py
nodestream/cli/commands/run.py
nodestream/cli/commands/run_migrations.py
nodestream/cli/commands/scaffold.py
nodestream/cli/commands/shared_options.py
nodestream/cli/commands/show.py
nodestream/cli/commands/show_migrations.py
nodestream/cli/commands/squash_migrations.py
nodestream/cli/operations/__init__.py
nodestream/cli/operations/add_pipeline_to_project.py
nodestream/cli/operations/commit_project_to_disk.py
nodestream/cli/operations/execute_migration.py
nodestream/cli/operations/generate_migration.py
nodestream/cli/operations/generate_pipeline_scaffold.py
nodestream/cli/operations/generate_squashed_migration.py
nodestream/cli/operations/initialize_logger.py
nodestream/cli/operations/initialize_project.py
nodestream/cli/operations/intitialize_metrics.py
nodestream/cli/operations/operation.py
nodestream/cli/operations/print_project_schema.py
nodestream/cli/operations/remove_pipeline_from_project.py
nodestream/cli/operations/run_audit.py
nodestream/cli/operations/run_copy.py
nodestream/cli/operations/run_pipeline.py
nodestream/cli/operations/run_project_cookiecutter.py
nodestream/cli/operations/show_pipelines.py
nodestream/compat.py
nodestream/databases/__init__.py
nodestream/databases/copy.py
nodestream/databases/database_connector.py
nodestream/databases/debounced_ingest_strategy.py
nodestream/databases/ingest_strategy.py
nodestream/databases/null.py
nodestream/databases/operation_debouncer.py
nodestream/databases/query_executor.py
nodestream/databases/query_executor_with_statistics.py
nodestream/databases/writer.py
nodestream/file_io.py
nodestream/interpreting/__init__.py
nodestream-0.14.17.dist-info/METADATA
nodestream-0.14.17.dist-info/WHEEL
nodestream-0.14.17.dist-info/entry_points.txt
nodestream-0.14.17.dist-info/licenses/LICENSE
nodestream-0.14.17.dist-info/RECORD
