Metadata-Version: 2.4
Name: nodestream
Version: 0.14.17
Summary: A Fast, Declarative ETL for Graph Databases.
License: GPL-3.0-only
License-File: LICENSE
Keywords: etl,neo4j,declarative,data,kafka,ingest
Author: Zach Probst
Author-email: Zach_Probst@intuit.com
Requires-Python: >=3.10,<4.0
Classifier: Development Status :: 4 - Beta
Classifier: Environment :: Console
Classifier: Intended Audience :: Developers
Classifier: Intended Audience :: Information Technology
Classifier: License :: OSI Approved :: GNU Affero General Public License v3
Classifier: License :: OSI Approved :: GNU General Public License v3 (GPLv3)
Classifier: Natural Language :: English
Classifier: Programming Language :: Python :: 3
Classifier: Programming Language :: Python :: 3.10
Classifier: Programming Language :: Python :: 3.11
Classifier: Programming Language :: Python :: 3.12
Classifier: Programming Language :: Python :: 3.13
Classifier: Programming Language :: Python :: 3.14
Classifier: Topic :: Database
Provides-Extra: prometheus
Provides-Extra: validation
Requires-Dist: Jinja2 (>=3,<4)
Requires-Dist: boto3 (>=1.34.127,<2.0.0)
Requires-Dist: cleo (>=2.0,<3.0)
Requires-Dist: confluent-kafka (>=2.5,<3.0)
Requires-Dist: cookiecutter (>=2.0,<3.0)
Requires-Dist: genson (>=1.3.0,<2.0.0) ; extra == "validation"
Requires-Dist: httpx (>=0.27,<0.28)
Requires-Dist: jmespath (>=1.0,<2.0)
Requires-Dist: jsonschema (>=4.23.0,<5.0.0) ; extra == "validation"
Requires-Dist: pandas (>=2,<3)
Requires-Dist: prometheus-client (>=0.21.1,<0.22.0) ; extra == "prometheus"
Requires-Dist: psutil (>=6.0,<7.0)
Requires-Dist: pyarrow (>=17.0.0,<19.0.0)
Requires-Dist: python-json-logger (>=2.0,<3.0)
Requires-Dist: pyyaml (>=6.0,<7.0)
Requires-Dist: schema (>=0.7,<0.8)
Requires-Dist: uvloop (>=0.17.0,<=0.21.0) ; sys_platform == "darwin"
Requires-Dist: uvloop (>=0.17.0,<=0.21.0) ; sys_platform == "linux"
Project-URL: Documentation, https://nodestream-proj.github.io/nodestream
Project-URL: Homepage, https://github.com/nodestream-proj/nodestream
Project-URL: Repository, https://github.com/nodestream-proj/nodestream
